{
  "project_info": {
    "project_number": "1052494936390",
    "project_id": "idea-bag-1482411280626"
  },
  "client": [
    {
      "client_info": {
        "mobilesdk_app_id": "1:1052494936390:android:1e96508d82d2446f",
        "android_client_info": {
          "package_name": "com.journal"
        }
      },
      "oauth_client": [
        {
          "client_id": "1052494936390-o42n53gd5nli0v9r19uqjsmn8t9dr9rb.apps.googleusercontent.com",
          "client_type": 1,
          "android_info": {
            "package_name": "com.journal",
            "certificate_hash": "7471AF61B95EC2CC2DED76217323FD1CDE2E2986"
          }
        },
        {
          "client_id": "1052494936390-rff04sjs8hdskebdc0lg4i4b029105pp.apps.googleusercontent.com",
          "client_type": 3
        }
      ],
      "api_key": [
        {
          "current_key": "AIzaSyD67wbiZ_VJc3DJ74Udx1oyLwh4QhBWM6A"
        }
      ],
      "services": {
        "analytics_service": {
          "status": 1
        },
        "appinvite_service": {
          "status": 1,
          "other_platform_oauth_client": []
        },
        "ads_service": {
          "status": 1
        }
      }
    }
  ],
  "configuration_version": "1"
}